lazydocs2/__init__.py
lazydocs2/__main__.py
lazydocs2/_about.py
lazydocs2/_cli.py
lazydocs2/generation.py
lazydocs2-0.1.2.dist-info/LICENSE
lazydocs2-0.1.2.dist-info/METADATA
lazydocs2-0.1.2.dist-info/WHEEL
lazydocs2-0.1.2.dist-info/entry_points.txt
lazydocs2-0.1.2.dist-info/RECORD
