Metadata-Version: 2.1
Name: lazydocs2
Version: 0.1.2
Summary: A fork of lazydocs for additional features
License: MIT
Author: khalidelborai
Author-email: elboraikhalid@gmail.com
Requires-Python: >=3.7,<4.0
Classifier: License :: OSI Approved :: MIT License
Classifier: Programming Language :: Python :: 3
Classifier: Programming Language :: Python :: 3.7
Classifier: Programming Language :: Python :: 3.8
Classifier: Programming Language :: Python :: 3.9
Classifier: Programming Language :: Python :: 3.10
Classifier: Programming Language :: Python :: 3.11
Requires-Dist: typer (>=0.9.0,<0.10.0)
